lygos_sdk/__init__.py
lygos_sdk/client.py
lygos_sdk/exceptions.py
lygos_sdk-0.1.0.dist-info/METADATA
lygos_sdk-0.1.0.dist-info/WHEEL
lygos_sdk-0.1.0.dist-info/top_level.txt
lygos_sdk-0.1.0.dist-info/RECORD
